CPU_L/src/UART_RX.v
module UART_RX (
    input clk,
    input reset,
    input rx,
    output reg [7:0] data_out,
    output reg rx_ready
);
    localparam BAUD_RATE =  25000000;//25000000 9600 115200
    localparam CLK_FREQ = 50000000;
    localparam BAUD_TICKS = CLK_FREQ / BAUD_RATE;
    localparam HALF_BAUD = BAUD_TICKS / 2;

    reg [15:0] baud_counter;
    reg [3:0] bit_index;
    reg [7:0] shift_reg;
    reg [1:0] state;

    localparam IDLE = 0, START = 1, DATA = 2, STOP = 3;

    always @(posedge clk or negedge reset) begin
        if (~reset) begin
            state <= IDLE;
            rx_ready <= 1'b0;
        end else begin
            case (state)
                IDLE: begin
                    rx_ready <= 1'b0;
                    if (rx == 1'b0) begin // обнаружение стартового бита
                        state <= START;
                        baud_counter <= HALF_BAUD - 1;
                    end
                end

                START: begin
                    if (baud_counter == 0) begin
                        // проверка, что это действительно старт
                        if (rx == 1'b0) begin
                            state <= DATA;
                            bit_index <= 0;
                            baud_counter <= BAUD_TICKS - 1;
                        end else begin
                            state <= IDLE; // ложный старт
                        end
                    end else begin
                        baud_counter <= baud_counter - 1;
                    end
                end

                DATA: begin
                    if (baud_counter == 0) begin
                        baud_counter <= BAUD_TICKS - 1;
                        shift_reg <= {rx, shift_reg[7:1]}; // сборка битов
                        if (bit_index == 7) begin
                            state <= STOP;
                        end else begin
                            bit_index <= bit_index + 1;
                        end
                    end else begin
                        baud_counter <= baud_counter - 1;
                    end
                end

                STOP: begin
                    if (baud_counter == 0) begin
                        if (rx == 1'b1) begin // проверка стоп-бита
                            data_out <= shift_reg;
                            rx_ready <= 1'b1;
                        end
                        state <= IDLE;
                    end else begin
                        baud_counter <= baud_counter - 1;
                    end
                end
            endcase
        end
    end
endmodule

CPU_L/src/UART_TX.v
module UART_TX (
    input clk,
    input reset,
    input tx_start,
    input [7:0] data_in,
    output reg tx,
    output reg tx_busy
);
    localparam BAUD_RATE = 25000000;
    localparam CLK_FREQ = 50000000; // 50 МГц
    localparam BAUD_TICKS = CLK_FREQ / BAUD_RATE; // 434 для 115200

    reg [15:0] baud_counter;
    reg [3:0] bit_index;
    reg [7:0] shift_reg;
    reg [1:0] state;

    localparam IDLE = 0, START = 1, DATA = 2, STOP = 3;

    always @(posedge clk or negedge reset) begin
        if (~reset) begin
            tx <= 1'b1;
            tx_busy <= 1'b0;
            state <= IDLE;
            baud_counter <= 0;
            bit_index <= 0;
        end else begin
            case (state)
                IDLE: begin
                    tx <= 1'b1;
                    tx_busy <= 1'b0;
                    if (tx_start) begin
                        shift_reg <= data_in;
                        state <= START;
                        tx_busy <= 1'b1;
                        baud_counter <= BAUD_TICKS - 1;
                    end
                end

                START: begin
                    tx <= 1'b0; // стартовый бит
                    if (baud_counter == 0) begin
                        baud_counter <= BAUD_TICKS - 1;
                        state <= DATA;
                        bit_index <= 0;
                    end else begin
                        baud_counter <= baud_counter - 1;
                    end
                end

                DATA: begin
                    tx <= shift_reg[0]; // младший бит вперед
                    if (baud_counter == 0) begin
                        baud_counter <= BAUD_TICKS - 1;
                        shift_reg <= {1'b0, shift_reg[7:1]}; // сдвиг
                        if (bit_index == 7) begin
                            state <= STOP;
                        end else begin
                            bit_index <= bit_index + 1;
                        end
                    end else begin
                        baud_counter <= baud_counter - 1;
                    end
                end

                STOP: begin
                    tx <= 1'b1;
                    if (baud_counter == 0) begin
                        state <= IDLE;
                    end else begin
                        baud_counter <= baud_counter - 1;
                    end
                end
            endcase
        end
    end
endmodule

CPU_L/src/mem1.v
module mem1(
    input           clk,
    input   [15:0]    adr,
    output  [7:0]    data_out
);

reg [7:0] data;

always @(*) begin
    case (adr)
        16'h0000: data <= 8'h30;
        16'h0001: data <= 8'h31;
        16'h0002: data <= 8'h32;
        16'h0003: data <= 8'h33;
        16'h0004: data <= 8'h34;
        16'h0005: data <= 8'h35;
        16'h0006: data <= 8'h36;
        16'h0007: data <= 8'h37;
        16'h0008: data <= 8'h38;
        16'h0009: data <= 8'h39;

        16'h000A: data <= 8'h41;
        16'h000B: data <= 8'h42;
        16'h000C: data <= 8'h43;
        16'h000D: data <= 8'h44;
        16'h000E: data <= 8'h45;
        16'h000F: data <= 8'h46;
        


        16'h0010: data <= 8'h4C;
        16'h0011: data <= 8'h45;
        16'h0012: data <= 8'h44;
        16'h0013: data <= 8'h20;


        default: begin
            data <= 8'h00;
        end

    endcase
end



assign data_out = data;

    
endmodule

CPU_L/src/out_manager1.v
module out_manager1(
    input               clk,
    input               TX_b,
    input       [2:0]   cmd_in,
    input       [7:0]   data_in,
    input               ready,
    output reg  [15:0]  data_out,
    output reg          gotov
);


reg [15:0]  cont = 0;
reg [3:0]   xc = 3;

reg [2:0]   cmd;
reg [7:0]   data;

reg stat = 1;

always @(posedge clk) begin
    

    case (stat)

        1'b0:begin
            if (~TX_b && gotov == 0) begin

                gotov <= 1;

                case (cmd)
                    3'b000: begin
                        if (cont < 4) begin
                            data_out <= 16'h0010 + cont;
                            cont <= cont + 1;
                            gotov <= 1;
                        end
                        else begin
                            if (xc != 0) begin
                                data_out <= data[xc] ;
                                xc      <= xc - 1;
                                gotov <= 1;
                            end
                            else  begin
                                stat <= 1;
                            end
                        end

                    end    
                endcase
                    
            end
            else begin
                gotov <= 0;
            end
        end

        1'b1:begin
            gotov <= 0;
            cont  <= 0;
            xc    <= 3;
            if (ready) begin
                stat <= 0;
                cmd <= cmd_in;
                data <= data_in;
            end
        end
        
    endcase
    
    
        
    
end
    
endmodule

CPU_L/src/tb_m1.v
module tb_m1();
    
reg clk = 0;
reg rst;

always #10 clk <= ~clk;

wire        bis;
wire [15:0]  data_out;
wire        gotov;

reg  [2:0]  cmd;
reg  [7:0] data;
reg         ready;

initial begin
$dumpfile("tb_m1.vcd");
$dumpvars(0, tb_m1);
#10
rst <= 0;
#10
rst <= 1;

#10
cmd <= 3'b000;
data<= 8'h03;
ready<=1'b1;
#10
ready<=1'b0;

#10000;
$finish;
end

out_manager1 uut(
    .clk(clk),
    .TX_b(bis),

    .cmd_in(cmd),
    .data_in(data),
    .ready(ready),

    .data_out(data_out),
    .gotov(gotov)

);

wire [7:0] da;

mem1 mm(
    .clk(clk),
    .adr(data_out),
    .data_out(da)
);

wire d;

UART_TX tx(
    .clk(clk),
    .reset(rst),
    .tx_start(gotov),
    .data_in(da),
    .tx(d),
    .tx_busy(bis)
);

wire [7:0] data_fin;
wire ready_fin;

UART_RX rx (
    .clk(clk),
    .reset(rst),
    .rx(d),
    .data_out(data_fin),
    .rx_ready(ready_fin)
);


endmodule

CPU_L/tb_m1.vcd
$date
	Fri Apr 03 19:17:52 2026
$end
$version
	Icarus Verilog
$end
$timescale
	1s
$end
$scope module tb_m1 $end
$var wire 1 ! ready_fin $end
$var wire 1 " gotov $end
$var wire 16 # data_out [15:0] $end
$var wire 8 $ data_fin [7:0] $end
$var wire 8 % da [7:0] $end
$var wire 1 & d $end
$var wire 1 ' bis $end
$var reg 1 ( clk $end
$var reg 3 ) cmd [2:0] $end
$var reg 8 * data [7:0] $end
$var reg 1 + ready $end
$var reg 1 , rst $end
$scope module mm $end
$var wire 1 ( clk $end
$var wire 8 - data_out [7:0] $end
$var wire 16 . adr [15:0] $end
$var reg 8 / data [7:0] $end
$upscope $end
$scope module rx $end
$var wire 1 ( clk $end
$var wire 1 , reset $end
$var wire 1 & rx $end
$var parameter 32 0 BAUD_RATE $end
$var parameter 32 1 BAUD_TICKS $end
$var parameter 32 2 CLK_FREQ $end
$var parameter 32 3 DATA $end
$var parameter 32 4 HALF_BAUD $end
$var parameter 32 5 IDLE $end
$var parameter 32 6 START $end
$var parameter 32 7 STOP $end
$var reg 16 8 baud_counter [15:0] $end
$var reg 4 9 bit_index [3:0] $end
$var reg 8 : data_out [7:0] $end
$var reg 1 ! rx_ready $end
$var reg 8 ; shift_reg [7:0] $end
$var reg 2 < state [1:0] $end
$upscope $end
$scope module tx $end
$var wire 1 ( clk $end
$var wire 8 = data_in [7:0] $end
$var wire 1 , reset $end
$var wire 1 " tx_start $end
$var parameter 32 > BAUD_RATE $end
$var parameter 32 ? BAUD_TICKS $end
$var parameter 32 @ CLK_FREQ $end
$var parameter 32 A DATA $end
$var parameter 32 B IDLE $end
$var parameter 32 C START $end
$var parameter 32 D STOP $end
$var reg 16 E baud_counter [15:0] $end
$var reg 4 F bit_index [3:0] $end
$var reg 8 G shift_reg [7:0] $end
$var reg 2 H state [1:0] $end
$var reg 1 & tx $end
$var reg 1 ' tx_busy $end
$upscope $end
$scope module uut $end
$var wire 1 ' TX_b $end
$var wire 1 ( clk $end
$var wire 3 I cmd_in [2:0] $end
$var wire 8 J data_in [7:0] $end
$var wire 1 + ready $end
$var reg 3 K cmd [2:0] $end
$var reg 16 L cont [15:0] $end
$var reg 8 M data [7:0] $end
$var reg 16 N data_out [15:0] $end
$var reg 1 " gotov $end
$var reg 1 O stat $end
$var reg 4 P xc [3:0] $end
$upscope $end
$upscope $end
$enddefinitions $end
$comment Show the parameter values. $end
$dumpall
b11 D
b1 C
b0 B
b10 A
b10111110101111000010000000 @
b10 ?
b1011111010111100001000000 >
b11 7
b1 6
b0 5
b1 4
b10 3
b10111110101111000010000000 2
b10 1
b1011111010111100001000000 0
$end
#0
$dumpvars
b11 P
1O
bx N
bx M
b0 L
bx K
bx J
bx I
bx H
bx G
bx F
bx E
bx =
bx <
bx ;
bx :
bx 9
bx 8
bx /
bx .
bx -
x,
x+
bx *
bx )
0(
x'
x&
bx %
bx $
bx #
x"
x!
$end
#10
b0 F
b0 E
b0 H
0'
1&
0!
b0 <
0"
0,
1(
#20
1,
0(
#30
b11 M
b0 K
0O
1+
b11 *
b11 J
b0 )
b0 I
1(
#40
0+
0(
#50
b1001100 %
b1001100 -
b1001100 =
b1001100 /
b1 L
b10000 #
b10000 .
b10000 N
1"
1(
#60
0(
#70
b1 E
1'
b1 H
b1001100 G
0"
1(
#80
0(
#90
b0 E
0&
1(
#100
0(
#110
b0 8
b1 <
b10 H
b1 E
1(
#120
0(
#130
b0 E
b1 8
b0 9
b10 <
1(
#140
0(
#150
b0 8
b1 F
b100110 G
b1 E
1(
#160
0(
#170
b0 E
b1 9
b0xxxxxxx ;
b1 8
1(
#180
0(
#190
b0 8
b10 F
b10011 G
b1 E
1(
#200
0(
#210
b0 E
1&
b10 9
b0xxxxxx ;
b1 8
1(
#220
0(
#230
b0 8
b11 F
b1001 G
b1 E
1(
#240
0(
#250
b0 E
b11 9
b100xxxxx ;
b1 8
1(
#260
0(
#270
b0 8
b100 F
b100 G
b1 E
1(
#280
0(
#290
b0 E
0&
b100 9
b1100xxxx ;
b1 8
1(
#300
0(
#310
b0 8
b101 F
b10 G
b1 E
1(
#320
0(
#330
b0 E
b101 9
b1100xxx ;
b1 8
1(
#340
0(
#350
b0 8
b110 F
b1 G
b1 E
1(
#360
0(
#370
b0 E
1&
b110 9
b1100xx ;
b1 8
1(
#380
0(
#390
b0 8
b111 F
b0 G
b1 E
1(
#400
0(
#410
b0 E
0&
b111 9
b1001100x ;
b1 8
1(
#420
0(
#430
b0 8
b11 H
b1 E
1(
#440
0(
#450
b0 E
1&
b11 <
b1001100 ;
b1 8
1(
#460
0(
#470
b0 8
b0 H
1(
#480
0(
#490
0'
b0 <
1!
b1001100 $
b1001100 :
1(
#500
0(
#510
b1000101 %
b1000101 -
b1000101 =
b1000101 /
0!
b10 L
b10001 #
b10001 .
b10001 N
1"
1(
#520
0(
#530
b1 E
1'
b1 H
b1000101 G
0"
1(
#540
0(
#550
b0 E
0&
1(
#560
0(
#570
b0 F
b10 H
b1 E
b1 <
1(
#580
0(
#590
b1 8
b0 9
b10 <
b0 E
1&
1(
#600
0(
#610
b1 F
b100010 G
b1 E
b0 8
1(
#620
0(
#630
b1 9
b10100110 ;
b1 8
b0 E
0&
1(
#640
0(
#650
b10 F
b10001 G
b1 E
b0 8
1(
#660
0(
#670
b10 9
b1010011 ;
b1 8
b0 E
1&
1(
#680
0(
#690
b11 F
b1000 G
b1 E
b0 8
1(
#700
0(
#710
b11 9
b10101001 ;
b1 8
b0 E
0&
1(
#720
0(
#730
b100 F
b100 G
b1 E
b0 8
1(
#740
0(
#750
b100 9
b1010100 ;
b1 8
b0 E
1(
#760
0(
#770
b101 F
b10 G
b1 E
b0 8
1(
#780
0(
#790
b101 9
b101010 ;
b1 8
b0 E
1(
#800
0(
#810
b110 F
b1 G
b1 E
b0 8
1(
#820
0(
#830
b110 9
b10101 ;
b1 8
b0 E
1&
1(
#840
0(
#850
b111 F
b0 G
b1 E
b0 8
1(
#860
0(
#870
b111 9
b10001010 ;
b1 8
b0 E
0&
1(
#880
0(
#890
b11 H
b1 E
b0 8
1(
#900
0(
#910
b11 <
b1000101 ;
b1 8
b0 E
1&
1(
#920
0(
#930
b0 H
b0 8
1(
#940
0(
#950
b0 <
1!
b1000101 $
b1000101 :
0'
1(
#960
0(
#970
b1000100 %
b1000100 -
b1000100 =
b1000100 /
0!
b11 L
b10010 #
b10010 .
b10010 N
1"
1(
#980
0(
#990
b1 E
1'
b1 H
b1000100 G
0"
1(
#1000
0(
#1010
b0 E
0&
1(
#1020
0(
#1030
b1 <
b0 F
b10 H
b1 E
1(
#1040
0(
#1050
b0 E
b1 8
b0 9
b10 <
1(
#1060
0(
#1070
b0 8
b1 F
b100010 G
b1 E
1(
#1080
0(
#1090
b0 E
b1 9
b100010 ;
b1 8
1(
#1100
0(
#1110
b0 8
b10 F
b10001 G
b1 E
1(
#1120
0(
#1130
b0 E
1&
b10 9
b10001 ;
b1 8
1(
#1140
0(
#1150
b0 8
b11 F
b1000 G
b1 E
1(
#1160
0(
#1170
b0 E
0&
b11 9
b10001000 ;
b1 8
1(
#1180
0(
#1190
b0 8
b100 F
b100 G
b1 E
1(
#1200
0(
#1210
b0 E
b100 9
b1000100 ;
b1 8
1(
#1220
0(
#1230
b0 8
b101 F
b10 G
b1 E
1(
#1240
0(
#1250
b0 E
b101 9
b100010 ;
b1 8
1(
#1260
0(
#1270
b0 8
b110 F
b1 G
b1 E
1(
#1280
0(
#1290
b0 E
1&
b110 9
b10001 ;
b1 8
1(
#1300
0(
#1310
b0 8
b111 F
b0 G
b1 E
1(
#1320
0(
#1330
b0 E
0&
b111 9
b10001000 ;
b1 8
1(
#1340
0(
#1350
b0 8
b11 H
b1 E
1(
#1360
0(
#1370
b0 E
1&
b11 <
b1000100 ;
b1 8
1(
#1380
0(
#1390
b0 8
b0 H
1(
#1400
0(
#1410
0'
b0 <
1!
b1000100 $
b1000100 :
1(
#1420
0(
#1430
b100000 %
b100000 -
b100000 =
b100000 /
0!
b100 L
b10011 #
b10011 .
b10011 N
1"
1(
#1440
0(
#1450
b1 E
1'
b1 H
b100000 G
0"
1(
#1460
0(
#1470
b0 E
0&
1(
#1480
0(
#1490
b0 F
b10 H
b1 E
b1 <
1(
#1500
0(
#1510
b1 8
b0 9
b10 <
b0 E
1(
#1520
0(
#1530
b1 F
b10000 G
b1 E
b0 8
1(
#1540
0(
#1550
b1 9
b100010 ;
b1 8
b0 E
1(
#1560
0(
#1570
b10 F
b1000 G
b1 E
b0 8
1(
#1580
0(
#1590
b10 9
b10001 ;
b1 8
b0 E
1(
#1600
0(
#1610
b11 F
b100 G
b1 E
b0 8
1(
#1620
0(
#1630
b11 9
b1000 ;
b1 8
b0 E
1(
#1640
0(
#1650
b100 F
b10 G
b1 E
b0 8
1(
#1660
0(
#1670
b100 9
b100 ;
b1 8
b0 E
1(
#1680
0(
#1690
b101 F
b1 G
b1 E
b0 8
1(
#1700
0(
#1710
b101 9
b10 ;
b1 8
b0 E
1&
1(
#1720
0(
#1730
b110 F
b0 G
b1 E
b0 8
1(
#1740
0(
#1750
b110 9
b10000001 ;
b1 8
b0 E
0&
1(
#1760
0(
#1770
b111 F
b1 E
b0 8
1(
#1780
0(
#1790
b111 9
b1000000 ;
b1 8
b0 E
1(
#1800
0(
#1810
b11 H
b1 E
b0 8
1(
#1820
0(
#1830
b11 <
b100000 ;
b1 8
b0 E
1&
1(
#1840
0(
#1850
b0 H
b0 8
1(
#1860
0(
#1870
b0 <
1!
b100000 $
b100000 :
0'
1(
#1880
0(
#1890
b110000 %
b110000 -
b110000 =
b110000 /
0!
b10 P
b0 #
b0 .
b0 N
1"
1(
#1900
0(
#1910
b1 E
1'
b1 H
b110000 G
0"
1(
#1920
0(
#1930
b0 E
0&
1(
#1940
0(
#1950
b1 <
b0 F
b10 H
b1 E
1(
#1960
0(
#1970
b0 E
b1 8
b0 9
b10 <
1(
#1980
0(
#1990
b0 8
b1 F
b11000 G
b1 E
1(
#2000
0(
#2010
b0 E
b1 9
b10000 ;
b1 8
1(
#2020
0(
#2030
b0 8
b10 F
b1100 G
b1 E
1(
#2040
0(
#2050
b0 E
b10 9
b1000 ;
b1 8
1(
#2060
0(
#2070
b0 8
b11 F
b110 G
b1 E
1(
#2080
0(
#2090
b0 E
b11 9
b100 ;
b1 8
1(
#2100
0(
#2110
b0 8
b100 F
b11 G
b1 E
1(
#2120
0(
#2130
b0 E
1&
b100 9
b10 ;
b1 8
1(
#2140
0(
#2150
b0 8
b101 F
b1 G
b1 E
1(
#2160
0(
#2170
b0 E
b101 9
b10000001 ;
b1 8
1(
#2180
0(
#2190
b0 8
b110 F
b0 G
b1 E
1(
#2200
0(
#2210
b0 E
0&
b110 9
b11000000 ;
b1 8
1(
#2220
0(
#2230
b0 8
b111 F
b1 E
1(
#2240
0(
#2250
b0 E
b111 9
b1100000 ;
b1 8
1(
#2260
0(
#2270
b0 8
b11 H
b1 E
1(
#2280
0(
#2290
b0 E
1&
b11 <
b110000 ;
b1 8
1(
#2300
0(
#2310
b0 8
b0 H
1(
#2320
0(
#2330
0'
b0 <
1!
b110000 $
b110000 :
1(
#2340
0(
#2350
0!
b1 P
1"
1(
#2360
0(
#2370
b1 E
1'
b1 H
b110000 G
0"
1(
#2380
0(
#2390
b0 E
0&
1(
#2400
0(
#2410
b0 F
b10 H
b1 E
b1 <
1(
#2420
0(
#2430
b1 8
b0 9
b10 <
b0 E
1(
#2440
0(
#2450
b1 F
b11000 G
b1 E
b0 8
1(
#2460
0(
#2470
b1 9
b11000 ;
b1 8
b0 E
1(
#2480
0(
#2490
b10 F
b1100 G
b1 E
b0 8
1(
#2500
0(
#2510
b10 9
b1100 ;
b1 8
b0 E
1(
#2520
0(
#2530
b11 F
b110 G
b1 E
b0 8
1(
#2540
0(
#2550
b11 9
b110 ;
b1 8
b0 E
1(
#2560
0(
#2570
b100 F
b11 G
b1 E
b0 8
1(
#2580
0(
#2590
b100 9
b11 ;
b1 8
b0 E
1&
1(
#2600
0(
#2610
b101 F
b1 G
b1 E
b0 8
1(
#2620
0(
#2630
b101 9
b10000001 ;
b1 8
b0 E
1(
#2640
0(
#2650
b110 F
b0 G
b1 E
b0 8
1(
#2660
0(
#2670
b110 9
b11000000 ;
b1 8
b0 E
0&
1(
#2680
0(
#2690
b111 F
b1 E
b0 8
1(
#2700
0(
#2710
b111 9
b1100000 ;
b1 8
b0 E
1(
#2720
0(
#2730
b11 H
b1 E
b0 8
1(
#2740
0(
#2750
b11 <
b110000 ;
b1 8
b0 E
1&
1(
#2760
0(
#2770
b0 H
b0 8
1(
#2780
0(
#2790
b0 <
1!
0'
1(
#2800
0(
#2810
b110001 %
b110001 -
b110001 =
b110001 /
0!
b0 P
b1 #
b1 .
b1 N
1"
1(
#2820
0(
#2830
b1 E
1'
b1 H
b110001 G
0"
1(
#2840
0(
#2850
b0 E
0&
1(
#2860
0(
#2870
b1 <
b0 F
b10 H
b1 E
1(
#2880
0(
#2890
b0 E
1&
b1 8
b0 9
b10 <
1(
#2900
0(
#2910
b0 8
b1 F
b11000 G
b1 E
1(
#2920
0(
#2930
b0 E
0&
b1 9
b10011000 ;
b1 8
1(
#2940
0(
#2950
b0 8
b10 F
b1100 G
b1 E
1(
#2960
0(
#2970
b0 E
b10 9
b1001100 ;
b1 8
1(
#2980
0(
#2990
b0 8
b11 F
b110 G
b1 E
1(
#3000
0(
#3010
b0 E
b11 9
b100110 ;
b1 8
1(
#3020
0(
#3030
b0 8
b100 F
b11 G
b1 E
1(
#3040
0(
#3050
b0 E
1&
b100 9
b10011 ;
b1 8
1(
#3060
0(
#3070
b0 8
b101 F
b1 G
b1 E
1(
#3080
0(
#3090
b0 E
b101 9
b10001001 ;
b1 8
1(
#3100
0(
#3110
b0 8
b110 F
b0 G
b1 E
1(
#3120
0(
#3130
b0 E
0&
b110 9
b11000100 ;
b1 8
1(
#3140
0(
#3150
b0 8
b111 F
b1 E
1(
#3160
0(
#3170
b0 E
b111 9
b1100010 ;
b1 8
1(
#3180
0(
#3190
b0 8
b11 H
b1 E
1(
#3200
0(
#3210
b0 E
1&
b11 <
b110001 ;
b1 8
1(
#3220
0(
#3230
b0 8
b0 H
1(
#3240
0(
#3250
0'
b0 <
1!
b110001 $
b110001 :
1(
#3260
0(
#3270
0!
1O
1"
1(
#3280
0(
#3290
b1 E
1'
b1 H
b110001 G
b11 P
b0 L
0"
1(
#3300
0(
#3310
b0 E
0&
1(
#3320
0(
#3330
b0 F
b10 H
b1 E
b1 <
1(
#3340
0(
#3350
b1 8
b0 9
b10 <
b0 E
1&
1(
#3360
0(
#3370
b1 F
b11000 G
b1 E
b0 8
1(
#3380
0(
#3390
b1 9
b10011000 ;
b1 8
b0 E
0&
1(
#3400
0(
#3410
b10 F
b1100 G
b1 E
b0 8
1(
#3420
0(
#3430
b10 9
b1001100 ;
b1 8
b0 E
1(
#3440
0(
#3450
b11 F
b110 G
b1 E
b0 8
1(
#3460
0(
#3470
b11 9
b100110 ;
b1 8
b0 E
1(
#3480
0(
#3490
b100 F
b11 G
b1 E
b0 8
1(
#3500
0(
#3510
b100 9
b10011 ;
b1 8
b0 E
1&
1(
#3520
0(
#3530
b101 F
b1 G
b1 E
b0 8
1(
#3540
0(
#3550
b101 9
b10001001 ;
b1 8
b0 E
1(
#3560
0(
#3570
b110 F
b0 G
b1 E
b0 8
1(
#3580
0(
#3590
b110 9
b11000100 ;
b1 8
b0 E
0&
1(
#3600
0(
#3610
b111 F
b1 E
b0 8
1(
#3620
0(
#3630
b111 9
b1100010 ;
b1 8
b0 E
1(
#3640
0(
#3650
b11 H
b1 E
b0 8
1(
#3660
0(
#3670
b11 <
b110001 ;
b1 8
b0 E
1&
1(
#3680
0(
#3690
b0 H
b0 8
1(
#3700
0(
#3710
b0 <
1!
0'
1(
#3720
0(
#3730
0!
1(
